aioabstractapi/__init__.py
aioabstractapi/base.py
aioabstractapi/const.py
aioabstractapi/email_api.py
aioabstractapi/iban_api.py
aioabstractapi/phone_api.py
aioabstractapi/vat_api.py
aioabstractapi/exceptions/__init__.py
aioabstractapi/exceptions/factory.py
aioabstractapi/models/__init__.py
aioabstractapi/models/_company.py
aioabstractapi/models/_country.py
aioabstractapi/models/_country_vat.py
aioabstractapi/models/_phone_formats.py
aioabstractapi/models/email.py
aioabstractapi/models/iban.py
aioabstractapi/models/phone.py
aioabstractapi/models/vat_calculate.py
aioabstractapi/models/vat_category.py
aioabstractapi/models/vat_validate.py
aioabstractapi-0.0.1.dist-info/METADATA
aioabstractapi-0.0.1.dist-info/WHEEL
aioabstractapi-0.0.1.dist-info/top_level.txt
aioabstractapi-0.0.1.dist-info/RECORD
