Metadata-Version: 2.1
Name: aioabstractapi
Version: 0.0.1
Summary: abstractapi.com asynchronous python wrapper
Home-page: https://github.com/ImmortalNameless/aioabstractapi
Author: Immortal
Author-email: pavelmarklev507@gmail.com
License: MIT
Project-URL: GitHub, https://github.com/ImmortalNameless
Keywords: abstract,aioabstract,abstract api,aioabstract api
Requires-Python: >=3.8
Requires-Dist: aiohttp (==3.8.3)
Requires-Dist: certifi (==2023.5.7)
Requires-Dist: pydantic (==2.4.1)
Requires-Dist: strenum (==0.4.10)
